ipyslack
