Metadata-Version: 1.1
Name: ipyslack
Version: 1.2.1
Summary: IPython magic for sending slack notifications
Home-page: https://github.com/konstantint/ipyslack
Author: Konstantin Tretyakov
Author-email: kt@ut.ee
License: MIT
Keywords: matplotlib plotting charts venn-diagrams
Platform: Platform Independent
Classifier: Development Status :: 4 - Beta
Classifier: Intended Audience :: Science/Research
Classifier: License :: OSI Approved :: MIT License
Classifier: Operating System :: OS Independent
Classifier: Programming Language :: Python :: 2
Classifier: Programming Language :: Python :: 3
Classifier: Framework :: IPython
